sunray/__init__.py
sunray/_internal/__init__.py
sunray/_internal/actor_mixin.py
sunray/_internal/callable.py
sunray/_internal/core.py
sunray/_internal/dag.py
sunray/_internal/io.py
sunray/_internal/remote.py
sunray/_internal/typing.py
sunray/_internal/util.py
sunray/dag.py
sunray/py.typed
sunray/util.py
sunray-0.13.0.dist-info/LICENSE
sunray-0.13.0.dist-info/METADATA
sunray-0.13.0.dist-info/WHEEL
sunray-0.13.0.dist-info/entry_points.txt
sunray-0.13.0.dist-info/RECORD
