Metadata-Version: 2.1
Name: sunray
Version: 0.13.0
Summary: More robust ray
Author: ZhengYu, Xu
Author-email: zen-xu@outlook.com
Requires-Python: >=3.9,<4.0
Classifier: Programming Language :: Python :: 3
Classifier: Programming Language :: Python :: 3.9
Classifier: Programming Language :: Python :: 3.10
Classifier: Programming Language :: Python :: 3.11
Classifier: Programming Language :: Python :: 3.12
Requires-Dist: ray[default] (>=2.20,<3.0) ; python_version >= "3.9" and python_version < "4.0"
Requires-Dist: typing-extensions (>=4.5.0,<5.0.0)
